[{"e":["https://knb.poolparty.biz/KNBMortgageTaxonomy/31","https://knb.poolparty.biz/KNBMortgageTaxonomy/59","https://knb.poolparty.biz/KNBMortgageTaxonomy/60","https://knb.poolparty.biz/KNBMortgageTaxonomy/61"],"d":["https://knb.poolparty.biz/KNBMortgageTaxonomy/31"],"de":["https://knb.poolparty.biz/KNBMortgageTaxonomy/31"],"het":["https://knb.poolparty.biz/KNBMortgageTaxonomy/59","https://knb.poolparty.biz/KNBMortgageTaxonomy/60","https://knb.poolparty.biz/KNBMortgageTaxonomy/61"],"he":["https://knb.poolparty.biz/KNBMortgageTaxonomy/59","https://knb.poolparty.biz/KNBMortgageTaxonomy/60","https://knb.poolparty.biz/KNBMortgageTaxonomy/61"],"h":["https://knb.poolparty.biz/KNBMortgageTaxonomy/59","https://knb.poolparty.biz/KNBMortgageTaxonomy/60","https://knb.poolparty.biz/KNBMortgageTaxonomy/61"],"et":["https://knb.poolparty.biz/KNBMortgageTaxonomy/59","https://knb.poolparty.biz/KNBMortgageTaxonomy/60","https://knb.poolparty.biz/KNBMortgageTaxonomy/61"],"t":["https://knb.poolparty.biz/KNBMortgageTaxonomy/59","https://knb.poolparty.biz/KNBMortgageTaxonomy/60","https://knb.poolparty.biz/KNBMortgageTaxonomy/61"]},{"hypotheeknemer":["https://knb.poolparty.biz/KNBMortgageTaxonomy/31"],"hypotheekneme":["https://knb.poolparty.biz/KNBMortgageTaxonomy/31"],"hypotheeknem":["https://knb.poolparty.biz/KNBMortgageTaxonomy/31"],"hypotheekne":["https://knb.poolparty.biz/KNBMortgageTaxonomy/31"],"hypotheekn":["https://knb.poolparty.biz/KNBMortgageTaxonomy/31"],"hypotheek":["https://knb.poolparty.biz/KNBMortgageTaxonomy/31"],"hypothee":["https://knb.poolparty.biz/KNBMortgageTaxonomy/31"],"hypothe":["https://knb.poolparty.biz/KNBMortgageTaxonomy/31"],"hypoth":["https://knb.poolparty.biz/KNBMortgageTaxonomy/31"],"hypot":["https://knb.poolparty.biz/KNBMortgageTaxonomy/31"],"hypo":["https://knb.poolparty.biz/KNBMortgageTaxonomy/31"],"hyp":["https://knb.poolparty.biz/KNBMortgageTaxonomy/31"],"hy":["https://knb.poolparty.biz/KNBMortgageTaxonomy/31"],"h":["https://knb.poolparty.biz/KNBMortgageTaxonomy/31"],"ypotheeknemer":["https://knb.poolparty.biz/KNBMortgageTaxonomy/31"],"ypotheekneme":["https://knb.poolparty.biz/KNBMortgageTaxonomy/31"],"ypotheeknem":["https://knb.poolparty.biz/KNBMortgageTaxonomy/31"],"ypotheekne":["https://knb.poolparty.biz/KNBMortgageTaxonomy/31"],"ypotheekn":["https://knb.poolparty.biz/KNBMortgageTaxonomy/31"],"ypotheek":["https://knb.poolparty.biz/KNBMortgageTaxonomy/31"],"ypothee":["https://knb.poolparty.biz/KNBMortgageTaxonomy/31"],"ypothe":["https://knb.poolparty.biz/KNBMortgageTaxonomy/31"],"ypoth":["https://knb.poolparty.biz/KNBMortgageTaxonomy/31"],"ypot":["https://knb.poolparty.biz/KNBMortgageTaxonomy/31"],"ypo":["https://knb.poolparty.biz/KNBMortgageTaxonomy/31"],"yp":["https://knb.poolparty.biz/KNBMortgageTaxonomy/31"],"y":["https://knb.poolparty.biz/KNBMortgageTaxonomy/31"],"potheeknemer":["https://knb.poolparty.biz/KNBMortgageTaxonomy/31"],"potheekneme":["https://knb.poolparty.biz/KNBMortgageTaxonomy/31"],"potheeknem":["https://knb.poolparty.biz/KNBMortgageTaxonomy/31"],"potheekne":["https://knb.poolparty.biz/KNBMortgageTaxonomy/31"],"potheekn":["https://knb.poolparty.biz/KNBMortgageTaxonomy/31"],"potheek":["https://knb.poolparty.biz/KNBMortgageTaxonomy/31"],"pothee":["https://knb.poolparty.biz/KNBMortgageTaxonomy/31"],"pothe":["https://knb.poolparty.biz/KNBMortgageTaxonomy/31"],"poth":["https://knb.poolparty.biz/KNBMortgageTaxonomy/31"],"pot":["https://knb.poolparty.biz/KNBMortgageTaxonomy/31"],"po":["https://knb.poolparty.biz/KNBMortgageTaxonomy/31"],"p":["https://knb.poolparty.biz/KNBMortgageTaxonomy/31"],"bedrag":["https://knb.poolparty.biz/KNBMortgageTaxonomy/59","https://knb.poolparty.biz/KNBMortgageTaxonomy/60"],"bedra":["https://knb.poolparty.biz/KNBMortgageTaxonomy/59","https://knb.poolparty.biz/KNBMortgageTaxonomy/60"],"bedr":["https://knb.poolparty.biz/KNBMortgageTaxonomy/59","https://knb.poolparty.biz/KNBMortgageTaxonomy/60"],"bed":["https://knb.poolparty.biz/KNBMortgageTaxonomy/59","https://knb.poolparty.biz/KNBMortgageTaxonomy/60"],"be":["https://knb.poolparty.biz/KNBMortgageTaxonomy/59","https://knb.poolparty.biz/KNBMortgageTaxonomy/60"],"b":["https://knb.poolparty.biz/KNBMortgageTaxonomy/59","https://knb.poolparty.biz/KNBMortgageTaxonomy/60"],"edrag":["https://knb.poolparty.biz/KNBMortgageTaxonomy/59","https://knb.poolparty.biz/KNBMortgageTaxonomy/60"],"edra":["https://knb.poolparty.biz/KNBMortgageTaxonomy/59","https://knb.poolparty.biz/KNBMortgageTaxonomy/60"],"edr":["https://knb.poolparty.biz/KNBMortgageTaxonomy/59","https://knb.poolparty.biz/KNBMortgageTaxonomy/60"],"ed":["https://knb.poolparty.biz/KNBMortgageTaxonomy/59","https://knb.poolparty.biz/KNBMortgageTaxonomy/60"],"dat":["https://knb.poolparty.biz/KNBMortgageTaxonomy/59"],"da":["https://knb.poolparty.biz/KNBMortgageTaxonomy/59"],"drag":["https://knb.poolparty.biz/KNBMortgageTaxonomy/60"],"dra":["https://knb.poolparty.biz/KNBMortgageTaxonomy/60"],"dr":["https://knb.poolparty.biz/KNBMortgageTaxonomy/60"],"d":["https://knb.poolparty.biz/KNBMortgageTaxonomy/60"],"ter":["https://knb.poolparty.biz/KNBMortgageTaxonomy/60"],"te":["https://knb.poolparty.biz/KNBMortgageTaxonomy/60"],"grootte":["https://knb.poolparty.biz/KNBMortgageTaxonomy/60"],"groott":["https://knb.poolparty.biz/KNBMortgageTaxonomy/60"],"groot":["https://knb.poolparty.biz/KNBMortgageTaxonomy/60"],"groo":["https://knb.poolparty.biz/KNBMortgageTaxonomy/60"],"gro":["https://knb.poolparty.biz/KNBMortgageTaxonomy/60"],"gr":["https://knb.poolparty.biz/KNBMortgageTaxonomy/60"],"recht":["https://knb.poolparty.biz/KNBMortgageTaxonomy/61"],"rech":["https://knb.poolparty.biz/KNBMortgageTaxonomy/61"],"rec":["https://knb.poolparty.biz/KNBMortgageTaxonomy/61"],"re":["https://knb.poolparty.biz/KNBMortgageTaxonomy/61"],"r":["https://knb.poolparty.biz/KNBMortgageTaxonomy/61"]},{"otheeknemer":["https://knb.poolparty.biz/KNBMortgageTaxonomy/31","https://knb.poolparty.biz/KNBMortgageTaxonomy/59"],"otheekneme":["https://knb.poolparty.biz/KNBMortgageTaxonomy/31","https://knb.poolparty.biz/KNBMortgageTaxonomy/59"],"otheeknem":["https://knb.poolparty.biz/KNBMortgageTaxonomy/31","https://knb.poolparty.biz/KNBMortgageTaxonomy/59"],"otheekne":["https://knb.poolparty.biz/KNBMortgageTaxonomy/31","https://knb.poolparty.biz/KNBMortgageTaxonomy/59"],"otheekn":["https://knb.poolparty.biz/KNBMortgageTaxonomy/31","https://knb.poolparty.biz/KNBMortgageTaxonomy/59"],"otheek":["https://knb.poolparty.biz/KNBMortgageTaxonomy/31","https://knb.poolparty.biz/KNBMortgageTaxonomy/59"],"othee":["https://knb.poolparty.biz/KNBMortgageTaxonomy/31","https://knb.poolparty.biz/KNBMortgageTaxonomy/59"],"othe":["https://knb.poolparty.biz/KNBMortgageTaxonomy/31","https://knb.poolparty.biz/KNBMortgageTaxonomy/59"],"oth":["https://knb.poolparty.biz/KNBMortgageTaxonomy/31","https://knb.poolparty.biz/KNBMortgageTaxonomy/59"],"ot":["https://knb.poolparty.biz/KNBMortgageTaxonomy/31","https://knb.poolparty.biz/KNBMortgageTaxonomy/59","https://knb.poolparty.biz/KNBMortgageTaxonomy/60"],"o":["https://knb.poolparty.biz/KNBMortgageTaxonomy/31","https://knb.poolparty.biz/KNBMortgageTaxonomy/59","https://knb.poolparty.biz/KNBMortgageTaxonomy/60"],"theeknemer":["https://knb.poolparty.biz/KNBMortgageTaxonomy/31"],"theekneme":["https://knb.poolparty.biz/KNBMortgageTaxonomy/31"],"theeknem":["https://knb.poolparty.biz/KNBMortgageTaxonomy/31"],"theekne":["https://knb.poolparty.biz/KNBMortgageTaxonomy/31"],"theekn":["https://knb.poolparty.biz/KNBMortgageTaxonomy/31"],"theek":["https://knb.poolparty.biz/KNBMortgageTaxonomy/31"],"thee":["https://knb.poolparty.biz/KNBMortgageTaxonomy/31"],"the":["https://knb.poolparty.biz/KNBMortgageTaxonomy/31"],"th":["https://knb.poolparty.biz/KNBMortgageTaxonomy/31"],"t":["https://knb.poolparty.biz/KNBMortgageTaxonomy/31"],"heeknemer":["https://knb.poolparty.biz/KNBMortgageTaxonomy/31"],"heekneme":["https://knb.poolparty.biz/KNBMortgageTaxonomy/31"],"heeknem":["https://knb.poolparty.biz/KNBMortgageTaxonomy/31"],"heekne":["https://knb.poolparty.biz/KNBMortgageTaxonomy/31"],"heekn":["https://knb.poolparty.biz/KNBMortgageTaxonomy/31"],"heek":["https://knb.poolparty.biz/KNBMortgageTaxonomy/31"],"hee":["https://knb.poolparty.biz/KNBMortgageTaxonomy/31"],"he":["https://knb.poolparty.biz/KNBMortgageTaxonomy/31"],"mag":["https://knb.poolparty.biz/KNBMortgageTaxonomy/31"],"ma":["https://knb.poolparty.biz/KNBMortgageTaxonomy/31","https://knb.poolparty.biz/KNBMortgageTaxonomy/60"],"ag":["https://knb.poolparty.biz/KNBMortgageTaxonomy/31","https://knb.poolparty.biz/KNBMortgageTaxonomy/59","https://knb.poolparty.biz/KNBMortgageTaxonomy/60"],"a":["https://knb.poolparty.biz/KNBMortgageTaxonomy/31","https://knb.poolparty.biz/KNBMortgageTaxonomy/59","https://knb.poolparty.biz/KNBMortgageTaxonomy/60","https://knb.poolparty.biz/KNBMortgageTaxonomy/61"],"niet":["https://knb.poolparty.biz/KNBMortgageTaxonomy/31"],"nie":["https://knb.poolparty.biz/KNBMortgageTaxonomy/31"],"ni":["https://knb.poolparty.biz/KNBMortgageTaxonomy/31"],"iet":["https://knb.poolparty.biz/KNBMortgageTaxonomy/31"],"ie":["https://knb.poolparty.biz/KNBMortgageTaxonomy/31"],"i":["https://knb.poolparty.biz/KNBMortgageTaxonomy/31","https://knb.poolparty.biz/KNBMortgageTaxonomy/59"],"meer":["https://knb.poolparty.biz/KNBMortgageTaxonomy/31"],"mee":["https://knb.poolparty.biz/KNBMortgageTaxonomy/31"],"drag":["https://knb.poolparty.biz/KNBMortgageTaxonomy/59"],"dra":["https://knb.poolparty.biz/KNBMortgageTaxonomy/59"],"dr":["https://knb.poolparty.biz/KNBMortgageTaxonomy/59"],"d":["https://knb.poolparty.biz/KNBMortgageTaxonomy/59"],"rag":["https://knb.poolparty.biz/KNBMortgageTaxonomy/59","https://knb.poolparty.biz/KNBMortgageTaxonomy/60"],"ra":["https://knb.poolparty.biz/KNBMortgageTaxonomy/59","https://knb.poolparty.biz/KNBMortgageTaxonomy/60"],"r":["https://knb.poolparty.biz/KNBMortgageTaxonomy/59","https://knb.poolparty.biz/KNBMortgageTaxonomy/60"],"at":["https://knb.poolparty.biz/KNBMortgageTaxonomy/59"],"een":["https://knb.poolparty.biz/KNBMortgageTaxonomy/59"],"ee":["https://knb.poolparty.biz/KNBMortgageTaxonomy/59"],"en":["https://knb.poolparty.biz/KNBMortgageTaxonomy/59"],"hypotheeknemer":["https://knb.poolparty.biz/KNBMortgageTaxonomy/59"],"hypotheekneme":["https://knb.poolparty.biz/KNBMortgageTaxonomy/59"],"hypotheeknem":["https://knb.poolparty.biz/KNBMortgageTaxonomy/59"],"hypotheekne":["https://knb.poolparty.biz/KNBMortgageTaxonomy/59"],"hypotheekn":["https://knb.poolparty.biz/KNBMortgageTaxonomy/59"],"hypotheek":["https://knb.poolparty.biz/KNBMortgageTaxonomy/59","https://knb.poolparty.biz/KNBMortgageTaxonomy/61"],"hypothee":["https://knb.poolparty.biz/KNBMortgageTaxonomy/59","https://knb.poolparty.biz/KNBMortgageTaxonomy/61"],"hypothe":["https://knb.poolparty.biz/KNBMortgageTaxonomy/59","https://knb.poolparty.biz/KNBMortgageTaxonomy/61"],"hypoth":["https://knb.poolparty.biz/KNBMortgageTaxonomy/59","https://knb.poolparty.biz/KNBMortgageTaxonomy/61"],"hypot":["https://knb.poolparty.biz/KNBMortgageTaxonomy/59","https://knb.poolparty.biz/KNBMortgageTaxonomy/61"],"hypo":["https://knb.poolparty.biz/KNBMortgageTaxonomy/59","https://knb.poolparty.biz/KNBMortgageTaxonomy/61"],"hyp":["https://knb.poolparty.biz/KNBMortgageTaxonomy/59","https://knb.poolparty.biz/KNBMortgageTaxonomy/61"],"hy":["https://knb.poolparty.biz/KNBMortgageTaxonomy/59","https://knb.poolparty.biz/KNBMortgageTaxonomy/61"],"ypotheeknemer":["https://knb.poolparty.biz/KNBMortgageTaxonomy/59"],"ypotheekneme":["https://knb.poolparty.biz/KNBMortgageTaxonomy/59"],"ypotheeknem":["https://knb.poolparty.biz/KNBMortgageTaxonomy/59"],"ypotheekne":["https://knb.poolparty.biz/KNBMortgageTaxonomy/59"],"ypotheekn":["https://knb.poolparty.biz/KNBMortgageTaxonomy/59"],"ypotheek":["https://knb.poolparty.biz/KNBMortgageTaxonomy/59","https://knb.poolparty.biz/KNBMortgageTaxonomy/61"],"ypothee":["https://knb.poolparty.biz/KNBMortgageTaxonomy/59","https://knb.poolparty.biz/KNBMortgageTaxonomy/61"],"ypothe":["https://knb.poolparty.biz/KNBMortgageTaxonomy/59","https://knb.poolparty.biz/KNBMortgageTaxonomy/61"],"ypoth":["https://knb.poolparty.biz/KNBMortgageTaxonomy/59","https://knb.poolparty.biz/KNBMortgageTaxonomy/61"],"ypot":["https://knb.poolparty.biz/KNBMortgageTaxonomy/59","https://knb.poolparty.biz/KNBMortgageTaxonomy/61"],"ypo":["https://knb.poolparty.biz/KNBMortgageTaxonomy/59","https://knb.poolparty.biz/KNBMortgageTaxonomy/61"],"yp":["https://knb.poolparty.biz/KNBMortgageTaxonomy/59","https://knb.poolparty.biz/KNBMortgageTaxonomy/61"],"y":["https://knb.poolparty.biz/KNBMortgageTaxonomy/59","https://knb.poolparty.biz/KNBMortgageTaxonomy/61"],"potheeknemer":["https://knb.poolparty.biz/KNBMortgageTaxonomy/59"],"potheekneme":["https://knb.poolparty.biz/KNBMortgageTaxonomy/59"],"potheeknem":["https://knb.poolparty.biz/KNBMortgageTaxonomy/59"],"potheekne":["https://knb.poolparty.biz/KNBMortgageTaxonomy/59"],"potheekn":["https://knb.poolparty.biz/KNBMortgageTaxonomy/59"],"potheek":["https://knb.poolparty.biz/KNBMortgageTaxonomy/59"],"pothee":["https://knb.poolparty.biz/KNBMortgageTaxonomy/59"],"pothe":["https://knb.poolparty.biz/KNBMortgageTaxonomy/59"],"poth":["https://knb.poolparty.biz/KNBMortgageTaxonomy/59"],"pot":["https://knb.poolparty.biz/KNBMortgageTaxonomy/59"],"po":["https://knb.poolparty.biz/KNBMortgageTaxonomy/59"],"p":["https://knb.poolparty.biz/KNBMortgageTaxonomy/59"],"naast":["https://knb.poolparty.biz/KNBMortgageTaxonomy/59"],"naas":["https://knb.poolparty.biz/KNBMortgageTaxonomy/59"],"naa":["https://knb.poolparty.biz/KNBMortgageTaxonomy/59"],"na":["https://knb.poolparty.biz/KNBMortgageTaxonomy/59"],"inschrijvingsbedrag":["https://knb.poolparty.biz/KNBMortgageTaxonomy/59"],"inschrijvingsbedra":["https://knb.poolparty.biz/KNBMortgageTaxonomy/59"],"inschrijvingsbedr":["https://knb.poolparty.biz/KNBMortgageTaxonomy/59"],"inschrijvingsbed":["https://knb.poolparty.biz/KNBMortgageTaxonomy/59"],"inschrijvingsbe":["https://knb.poolparty.biz/KNBMortgageTaxonomy/59"],"inschrijvingsb":["https://knb.poolparty.biz/KNBMortgageTaxonomy/59"],"inschrijvings":["https://knb.poolparty.biz/KNBMortgageTaxonomy/59"],"inschrijving":["https://knb.poolparty.biz/KNBMortgageTaxonomy/59"],"inschrijvin":["https://knb.poolparty.biz/KNBMortgageTaxonomy/59"],"inschrijvi":["https://knb.poolparty.biz/KNBMortgageTaxonomy/59"],"inschrijv":["https://knb.poolparty.biz/KNBMortgageTaxonomy/59"],"inschrij":["https://knb.poolparty.biz/KNBMortgageTaxonomy/59"],"inschri":["https://knb.poolparty.biz/KNBMortgageTaxonomy/59"],"inschr":["https://knb.poolparty.biz/KNBMortgageTaxonomy/59"],"insch":["https://knb.poolparty.biz/KNBMortgageTaxonomy/59"],"insc":["https://knb.poolparty.biz/KNBMortgageTaxonomy/59"],"ins":["https://knb.poolparty.biz/KNBMortgageTaxonomy/59"],"in":["https://knb.poolparty.biz/KNBMortgageTaxonomy/59"],"nschrijvingsbedrag":["https://knb.poolparty.biz/KNBMortgageTaxonomy/59"],"nschrijvingsbedra":["https://knb.poolparty.biz/KNBMortgageTaxonomy/59"],"nschrijvingsbedr":["https://knb.poolparty.biz/KNBMortgageTaxonomy/59"],"nschrijvingsbed":["https://knb.poolparty.biz/KNBMortgageTaxonomy/59"],"nschrijvingsbe":["https://knb.poolparty.biz/KNBMortgageTaxonomy/59"],"nschrijvingsb":["https://knb.poolparty.biz/KNBMortgageTaxonomy/59"],"nschrijvings":["https://knb.poolparty.biz/KNBMortgageTaxonomy/59"],"nschrijving":["https://knb.poolparty.biz/KNBMortgageTaxonomy/59"],"nschrijvin":["https://knb.poolparty.biz/KNBMortgageTaxonomy/59"],"nschrijvi":["https://knb.poolparty.biz/KNBMortgageTaxonomy/59"],"nschrijv":["https://knb.poolparty.biz/KNBMortgageTaxonomy/59"],"nschrij":["https://knb.poolparty.biz/KNBMortgageTaxonomy/59"],"nschri":["https://knb.poolparty.biz/KNBMortgageTaxonomy/59"],"nschr":["https://knb.poolparty.biz/KNBMortgageTaxonomy/59"],"nsch":["https://knb.poolparty.biz/KNBMortgageTaxonomy/59"],"nsc":["https://knb.poolparty.biz/KNBMortgageTaxonomy/59"],"ns":["https://knb.poolparty.biz/KNBMortgageTaxonomy/59"],"g":["https://knb.poolparty.biz/KNBMortgageTaxonomy/60"],"er":["https://knb.poolparty.biz/KNBMortgageTaxonomy/60"],"rootte":["https://knb.poolparty.biz/KNBMortgageTaxonomy/60"],"roott":["https://knb.poolparty.biz/KNBMortgageTaxonomy/60"],"root":["https://knb.poolparty.biz/KNBMortgageTaxonomy/60"],"roo":["https://knb.poolparty.biz/KNBMortgageTaxonomy/60"],"ro":["https://knb.poolparty.biz/KNBMortgageTaxonomy/60"],"ootte":["https://knb.poolparty.biz/KNBMortgageTaxonomy/60"],"oott":["https://knb.poolparty.biz/KNBMortgageTaxonomy/60"],"oot":["https://knb.poolparty.biz/KNBMortgageTaxonomy/60"],"oo":["https://knb.poolparty.biz/KNBMortgageTaxonomy/60"],"otte":["https://knb.poolparty.biz/KNBMortgageTaxonomy/60"],"ott":["https://knb.poolparty.biz/KNBMortgageTaxonomy/60"],"waarvan":["https://knb.poolparty.biz/KNBMortgageTaxonomy/60"],"waarva":["https://knb.poolparty.biz/KNBMortgageTaxonomy/60"],"waarv":["https://knb.poolparty.biz/KNBMortgageTaxonomy/60"],"waar":["https://knb.poolparty.biz/KNBMortgageTaxonomy/60"],"waa":["https://knb.poolparty.biz/KNBMortgageTaxonomy/60"],"wa":["https://knb.poolparty.biz/KNBMortgageTaxonomy/60"],"w":["https://knb.poolparty.biz/KNBMortgageTaxonomy/60"],"aarvan":["https://knb.poolparty.biz/KNBMortgageTaxonomy/60"],"aarva":["https://knb.poolparty.biz/KNBMortgageTaxonomy/60"],"aarv":["https://knb.poolparty.biz/KNBMortgageTaxonomy/60"],"aar":["https://knb.poolparty.biz/KNBMortgageTaxonomy/60"],"aa":["https://knb.poolparty.biz/KNBMortgageTaxonomy/60"],"arvan":["https://knb.poolparty.biz/KNBMortgageTaxonomy/60"],"arva":["https://knb.poolparty.biz/KNBMortgageTaxonomy/60"],"arv":["https://knb.poolparty.biz/KNBMortgageTaxonomy/60"],"ar":["https://knb.poolparty.biz/KNBMortgageTaxonomy/60"],"maximaal":["https://knb.poolparty.biz/KNBMortgageTaxonomy/60"],"maximaa":["https://knb.poolparty.biz/KNBMortgageTaxonomy/60"],"maxima":["https://knb.poolparty.biz/KNBMortgageTaxonomy/60"],"maxim":["https://knb.poolparty.biz/KNBMortgageTaxonomy/60"],"maxi":["https://knb.poolparty.biz/KNBMortgageTaxonomy/60"],"max":["https://knb.poolparty.biz/KNBMortgageTaxonomy/60"],"m":["https://knb.poolparty.biz/KNBMortgageTaxonomy/60"],"aximaal":["https://knb.poolparty.biz/KNBMortgageTaxonomy/60"],"aximaa":["https://knb.poolparty.biz/KNBMortgageTaxonomy/60"],"axima":["https://knb.poolparty.biz/KNBMortgageTaxonomy/60"],"axim":["https://knb.poolparty.biz/KNBMortgageTaxonomy/60"],"axi":["https://knb.poolparty.biz/KNBMortgageTaxonomy/60"],"ax":["https://knb.poolparty.biz/KNBMortgageTaxonomy/60"],"ximaal":["https://knb.poolparty.biz/KNBMortgageTaxonomy/60"],"ximaa":["https://knb.poolparty.biz/KNBMortgageTaxonomy/60"],"xima":["https://knb.poolparty.biz/KNBMortgageTaxonomy/60"],"xim":["https://knb.poolparty.biz/KNBMortgageTaxonomy/60"],"xi":["https://knb.poolparty.biz/KNBMortgageTaxonomy/60"],"x":["https://knb.poolparty.biz/KNBMortgageTaxonomy/60"],"opbrengst":["https://knb.poolparty.biz/KNBMortgageTaxonomy/60"],"opbrengs":["https://knb.poolparty.biz/KNBMortgageTaxonomy/60"],"opbreng":["https://knb.poolparty.biz/KNBMortgageTaxonomy/60"],"opbren":["https://knb.poolparty.biz/KNBMortgageTaxonomy/60"],"opbre":["https://knb.poolparty.biz/KNBMortgageTaxonomy/60"],"opbr":["https://knb.poolparty.biz/KNBMortgageTaxonomy/60"],"opb":["https://knb.poolparty.biz/KNBMortgageTaxonomy/60"],"op":["https://knb.poolparty.biz/KNBMortgageTaxonomy/60"],"echt":["https://knb.poolparty.biz/KNBMortgageTaxonomy/61"],"ech":["https://knb.poolparty.biz/KNBMortgageTaxonomy/61"],"ec":["https://knb.poolparty.biz/KNBMortgageTaxonomy/61"],"cht":["https://knb.poolparty.biz/KNBMortgageTaxonomy/61"],"ch":["https://knb.poolparty.biz/KNBMortgageTaxonomy/61"],"c":["https://knb.poolparty.biz/KNBMortgageTaxonomy/61"],"van":["https://knb.poolparty.biz/KNBMortgageTaxonomy/61"],"va":["https://knb.poolparty.biz/KNBMortgageTaxonomy/61"],"v":["https://knb.poolparty.biz/KNBMortgageTaxonomy/61"],"an":["https://knb.poolparty.biz/KNBMortgageTaxonomy/61"]},{"eeknemer":["https://knb.poolparty.biz/KNBMortgageTaxonomy/31","https://knb.poolparty.biz/KNBMortgageTaxonomy/59"],"eekneme":["https://knb.poolparty.biz/KNBMortgageTaxonomy/31","https://knb.poolparty.biz/KNBMortgageTaxonomy/59"],"eeknem":["https://knb.poolparty.biz/KNBMortgageTaxonomy/31","https://knb.poolparty.biz/KNBMortgageTaxonomy/59"],"eekne":["https://knb.poolparty.biz/KNBMortgageTaxonomy/31","https://knb.poolparty.biz/KNBMortgageTaxonomy/59"],"eekn":["https://knb.poolparty.biz/KNBMortgageTaxonomy/31","https://knb.poolparty.biz/KNBMortgageTaxonomy/59"],"eek":["https://knb.poolparty.biz/KNBMortgageTaxonomy/31","https://knb.poolparty.biz/KNBMortgageTaxonomy/59"],"ee":["https://knb.poolparty.biz/KNBMortgageTaxonomy/31"],"eknemer":["https://knb.poolparty.biz/KNBMortgageTaxonomy/31","https://knb.poolparty.biz/KNBMortgageTaxonomy/59"],"ekneme":["https://knb.poolparty.biz/KNBMortgageTaxonomy/31","https://knb.poolparty.biz/KNBMortgageTaxonomy/59"],"eknem":["https://knb.poolparty.biz/KNBMortgageTaxonomy/31","https://knb.poolparty.biz/KNBMortgageTaxonomy/59"],"ekne":["https://knb.poolparty.biz/KNBMortgageTaxonomy/31","https://knb.poolparty.biz/KNBMortgageTaxonomy/59"],"ekn":["https://knb.poolparty.biz/KNBMortgageTaxonomy/31","https://knb.poolparty.biz/KNBMortgageTaxonomy/59"],"ek":["https://knb.poolparty.biz/KNBMortgageTaxonomy/31","https://knb.poolparty.biz/KNBMortgageTaxonomy/59"],"knemer":["https://knb.poolparty.biz/KNBMortgageTaxonomy/31"],"kneme":["https://knb.poolparty.biz/KNBMortgageTaxonomy/31"],"knem":["https://knb.poolparty.biz/KNBMortgageTaxonomy/31"],"kne":["https://knb.poolparty.biz/KNBMortgageTaxonomy/31"],"kn":["https://knb.poolparty.biz/KNBMortgageTaxonomy/31"],"k":["https://knb.poolparty.biz/KNBMortgageTaxonomy/31"],"nemer":["https://knb.poolparty.biz/KNBMortgageTaxonomy/31"],"neme":["https://knb.poolparty.biz/KNBMortgageTaxonomy/31"],"nem":["https://knb.poolparty.biz/KNBMortgageTaxonomy/31"],"ne":["https://knb.poolparty.biz/KNBMortgageTaxonomy/31"],"n":["https://knb.poolparty.biz/KNBMortgageTaxonomy/31","https://knb.poolparty.biz/KNBMortgageTaxonomy/59","https://knb.poolparty.biz/KNBMortgageTaxonomy/60","https://knb.poolparty.biz/KNBMortgageTaxonomy/61"],"g":["https://knb.poolparty.biz/KNBMortgageTaxonomy/31","https://knb.poolparty.biz/KNBMortgageTaxonomy/59","https://knb.poolparty.biz/KNBMortgageTaxonomy/61"],"et":["https://knb.poolparty.biz/KNBMortgageTaxonomy/31"],"eer":["https://knb.poolparty.biz/KNBMortgageTaxonomy/31"],"het":["https://knb.poolparty.biz/KNBMortgageTaxonomy/31"],"bedrag":["https://knb.poolparty.biz/KNBMortgageTaxonomy/31"],"bedra":["https://knb.poolparty.biz/KNBMortgageTaxonomy/31"],"bedr":["https://knb.poolparty.biz/KNBMortgageTaxonomy/31"],"bed":["https://knb.poolparty.biz/KNBMortgageTaxonomy/31"],"be":["https://knb.poolparty.biz/KNBMortgageTaxonomy/31"],"b":["https://knb.poolparty.biz/KNBMortgageTaxonomy/31"],"edrag":["https://knb.poolparty.biz/KNBMortgageTaxonomy/31"],"edra":["https://knb.poolparty.biz/KNBMortgageTaxonomy/31"],"edr":["https://knb.poolparty.biz/KNBMortgageTaxonomy/31"],"ed":["https://knb.poolparty.biz/KNBMortgageTaxonomy/31"],"theeknemer":["https://knb.poolparty.biz/KNBMortgageTaxonomy/59"],"theekneme":["https://knb.poolparty.biz/KNBMortgageTaxonomy/59"],"theeknem":["https://knb.poolparty.biz/KNBMortgageTaxonomy/59"],"theekne":["https://knb.poolparty.biz/KNBMortgageTaxonomy/59"],"theekn":["https://knb.poolparty.biz/KNBMortgageTaxonomy/59"],"theek":["https://knb.poolparty.biz/KNBMortgageTaxonomy/59","https://knb.poolparty.biz/KNBMortgageTaxonomy/61"],"thee":["https://knb.poolparty.biz/KNBMortgageTaxonomy/59","https://knb.poolparty.biz/KNBMortgageTaxonomy/61"],"the":["https://knb.poolparty.biz/KNBMortgageTaxonomy/59","https://knb.poolparty.biz/KNBMortgageTaxonomy/61"],"th":["https://knb.poolparty.biz/KNBMortgageTaxonomy/59","https://knb.poolparty.biz/KNBMortgageTaxonomy/61"],"heeknemer":["https://knb.poolparty.biz/KNBMortgageTaxonomy/59"],"heekneme":["https://knb.poolparty.biz/KNBMortgageTaxonomy/59"],"heeknem":["https://knb.poolparty.biz/KNBMortgageTaxonomy/59"],"heekne":["https://knb.poolparty.biz/KNBMortgageTaxonomy/59"],"heekn":["https://knb.poolparty.biz/KNBMortgageTaxonomy/59"],"heek":["https://knb.poolparty.biz/KNBMortgageTaxonomy/59"],"hee":["https://knb.poolparty.biz/KNBMortgageTaxonomy/59"],"aast":["https://knb.poolparty.biz/KNBMortgageTaxonomy/59"],"aas":["https://knb.poolparty.biz/KNBMortgageTaxonomy/59"],"aa":["https://knb.poolparty.biz/KNBMortgageTaxonomy/59"],"ast":["https://knb.poolparty.biz/KNBMortgageTaxonomy/59"],"as":["https://knb.poolparty.biz/KNBMortgageTaxonomy/59"],"st":["https://knb.poolparty.biz/KNBMortgageTaxonomy/59"],"s":["https://knb.poolparty.biz/KNBMortgageTaxonomy/59"],"schrijvingsbedrag":["https://knb.poolparty.biz/KNBMortgageTaxonomy/59"],"schrijvingsbedra":["https://knb.poolparty.biz/KNBMortgageTaxonomy/59"],"schrijvingsbedr":["https://knb.poolparty.biz/KNBMortgageTaxonomy/59"],"schrijvingsbed":["https://knb.poolparty.biz/KNBMortgageTaxonomy/59"],"schrijvingsbe":["https://knb.poolparty.biz/KNBMortgageTaxonomy/59"],"schrijvingsb":["https://knb.poolparty.biz/KNBMortgageTaxonomy/59"],"schrijvings":["https://knb.poolparty.biz/KNBMortgageTaxonomy/59"],"schrijving":["https://knb.poolparty.biz/KNBMortgageTaxonomy/59"],"schrijvin":["https://knb.poolparty.biz/KNBMortgageTaxonomy/59"],"schrijvi":["https://knb.poolparty.biz/KNBMortgageTaxonomy/59"],"schrijv":["https://knb.poolparty.biz/KNBMortgageTaxonomy/59"],"schrij":["https://knb.poolparty.biz/KNBMortgageTaxonomy/59"],"schri":["https://knb.poolparty.biz/KNBMortgageTaxonomy/59"],"schr":["https://knb.poolparty.biz/KNBMortgageTaxonomy/59"],"sch":["https://knb.poolparty.biz/KNBMortgageTaxonomy/59"],"sc":["https://knb.poolparty.biz/KNBMortgageTaxonomy/59"],"chrijvingsbedrag":["https://knb.poolparty.biz/KNBMortgageTaxonomy/59"],"chrijvingsbedra":["https://knb.poolparty.biz/KNBMortgageTaxonomy/59"],"chrijvingsbedr":["https://knb.poolparty.biz/KNBMortgageTaxonomy/59"],"chrijvingsbed":["https://knb.poolparty.biz/KNBMortgageTaxonomy/59"],"chrijvingsbe":["https://knb.poolparty.biz/KNBMortgageTaxonomy/59"],"chrijvingsb":["https://knb.poolparty.biz/KNBMortgageTaxonomy/59"],"chrijvings":["https://knb.poolparty.biz/KNBMortgageTaxonomy/59"],"chrijving":["https://knb.poolparty.biz/KNBMortgageTaxonomy/59"],"chrijvin":["https://knb.poolparty.biz/KNBMortgageTaxonomy/59"],"chrijvi":["https://knb.poolparty.biz/KNBMortgageTaxonomy/59"],"chrijv":["https://knb.poolparty.biz/KNBMortgageTaxonomy/59"],"chrij":["https://knb.poolparty.biz/KNBMortgageTaxonomy/59"],"chri":["https://knb.poolparty.biz/KNBMortgageTaxonomy/59"],"chr":["https://knb.poolparty.biz/KNBMortgageTaxonomy/59"],"ch":["https://knb.poolparty.biz/KNBMortgageTaxonomy/59"],"c":["https://knb.poolparty.biz/KNBMortgageTaxonomy/59"],"hrijvingsbedrag":["https://knb.poolparty.biz/KNBMortgageTaxonomy/59"],"hrijvingsbedra":["https://knb.poolparty.biz/KNBMortgageTaxonomy/59"],"hrijvingsbedr":["https://knb.poolparty.biz/KNBMortgageTaxonomy/59"],"hrijvingsbed":["https://knb.poolparty.biz/KNBMortgageTaxonomy/59"],"hrijvingsbe":["https://knb.poolparty.biz/KNBMortgageTaxonomy/59"],"hrijvingsb":["https://knb.poolparty.biz/KNBMortgageTaxonomy/59"],"hrijvings":["https://knb.poolparty.biz/KNBMortgageTaxonomy/59"],"hrijving":["https://knb.poolparty.biz/KNBMortgageTaxonomy/59"],"hrijvin":["https://knb.poolparty.biz/KNBMortgageTaxonomy/59"],"hrijvi":["https://knb.poolparty.biz/KNBMortgageTaxonomy/59"],"hrijv":["https://knb.poolparty.biz/KNBMortgageTaxonomy/59"],"hrij":["https://knb.poolparty.biz/KNBMortgageTaxonomy/59"],"hri":["https://knb.poolparty.biz/KNBMortgageTaxonomy/59"],"hr":["https://knb.poolparty.biz/KNBMortgageTaxonomy/59"],"rijvingsbedrag":["https://knb.poolparty.biz/KNBMortgageTaxonomy/59"],"rijvingsbedra":["https://knb.poolparty.biz/KNBMortgageTaxonomy/59"],"rijvingsbedr":["https://knb.poolparty.biz/KNBMortgageTaxonomy/59"],"rijvingsbed":["https://knb.poolparty.biz/KNBMortgageTaxonomy/59"],"rijvingsbe":["https://knb.poolparty.biz/KNBMortgageTaxonomy/59"],"rijvingsb":["https://knb.poolparty.biz/KNBMortgageTaxonomy/59"],"rijvings":["https://knb.poolparty.biz/KNBMortgageTaxonomy/59"],"rijving":["https://knb.poolparty.biz/KNBMortgageTaxonomy/59"],"rijvin":["https://knb.poolparty.biz/KNBMortgageTaxonomy/59"],"rijvi":["https://knb.poolparty.biz/KNBMortgageTaxonomy/59"],"rijv":["https://knb.poolparty.biz/KNBMortgageTaxonomy/59"],"rij":["https://knb.poolparty.biz/KNBMortgageTaxonomy/59"],"ri":["https://knb.poolparty.biz/KNBMortgageTaxonomy/59"],"ijvingsbedrag":["https://knb.poolparty.biz/KNBMortgageTaxonomy/59"],"ijvingsbedra":["https://knb.poolparty.biz/KNBMortgageTaxonomy/59"],"ijvingsbedr":["https://knb.poolparty.biz/KNBMortgageTaxonomy/59"],"ijvingsbed":["https://knb.poolparty.biz/KNBMortgageTaxonomy/59"],"ijvingsbe":["https://knb.poolparty.biz/KNBMortgageTaxonomy/59"],"ijvingsb":["https://knb.poolparty.biz/KNBMortgageTaxonomy/59"],"ijvings":["https://knb.poolparty.biz/KNBMortgageTaxonomy/59"],"ijving":["https://knb.poolparty.biz/KNBMortgageTaxonomy/59"],"ijvin":["https://knb.poolparty.biz/KNBMortgageTaxonomy/59"],"ijvi":["https://knb.poolparty.biz/KNBMortgageTaxonomy/59"],"ijv":["https://knb.poolparty.biz/KNBMortgageTaxonomy/59"],"ij":["https://knb.poolparty.biz/KNBMortgageTaxonomy/59"],"tte":["https://knb.poolparty.biz/KNBMortgageTaxonomy/60"],"tt":["https://knb.poolparty.biz/KNBMortgageTaxonomy/60"],"rvan":["https://knb.poolparty.biz/KNBMortgageTaxonomy/60"],"rva":["https://knb.poolparty.biz/KNBMortgageTaxonomy/60"],"rv":["https://knb.poolparty.biz/KNBMortgageTaxonomy/60"],"van":["https://knb.poolparty.biz/KNBMortgageTaxonomy/60"],"va":["https://knb.poolparty.biz/KNBMortgageTaxonomy/60"],"v":["https://knb.poolparty.biz/KNBMortgageTaxonomy/60"],"an":["https://knb.poolparty.biz/KNBMortgageTaxonomy/60"],"imaal":["https://knb.poolparty.biz/KNBMortgageTaxonomy/60"],"imaa":["https://knb.poolparty.biz/KNBMortgageTaxonomy/60"],"ima":["https://knb.poolparty.biz/KNBMortgageTaxonomy/60"],"im":["https://knb.poolparty.biz/KNBMortgageTaxonomy/60"],"i":["https://knb.poolparty.biz/KNBMortgageTaxonomy/60"],"maal":["https://knb.poolparty.biz/KNBMortgageTaxonomy/60"],"maa":["https://knb.poolparty.biz/KNBMortgageTaxonomy/60"],"aal":["https://knb.poolparty.biz/KNBMortgageTaxonomy/60"],"de":["https://knb.poolparty.biz/KNBMortgageTaxonomy/60"],"pbrengst":["https://knb.poolparty.biz/KNBMortgageTaxonomy/60"],"pbrengs":["https://knb.poolparty.biz/KNBMortgageTaxonomy/60"],"pbreng":["https://knb.poolparty.biz/KNBMortgageTaxonomy/60"],"pbren":["https://knb.poolparty.biz/KNBMortgageTaxonomy/60"],"pbre":["https://knb.poolparty.biz/KNBMortgageTaxonomy/60"],"pbr":["https://knb.poolparty.biz/KNBMortgageTaxonomy/60"],"pb":["https://knb.poolparty.biz/KNBMortgageTaxonomy/60"],"p":["https://knb.poolparty.biz/KNBMortgageTaxonomy/60","https://knb.poolparty.biz/KNBMortgageTaxonomy/61"],"brengst":["https://knb.poolparty.biz/KNBMortgageTaxonomy/60"],"brengs":["https://knb.poolparty.biz/KNBMortgageTaxonomy/60"],"breng":["https://knb.poolparty.biz/KNBMortgageTaxonomy/60"],"bren":["https://knb.poolparty.biz/KNBMortgageTaxonomy/60"],"bre":["https://knb.poolparty.biz/KNBMortgageTaxonomy/60"],"br":["https://knb.poolparty.biz/KNBMortgageTaxonomy/60"],"rengst":["https://knb.poolparty.biz/KNBMortgageTaxonomy/60"],"rengs":["https://knb.poolparty.biz/KNBMortgageTaxonomy/60"],"reng":["https://knb.poolparty.biz/KNBMortgageTaxonomy/60"],"ren":["https://knb.poolparty.biz/KNBMortgageTaxonomy/60"],"re":["https://knb.poolparty.biz/KNBMortgageTaxonomy/60"],"engst":["https://knb.poolparty.biz/KNBMortgageTaxonomy/60"],"engs":["https://knb.poolparty.biz/KNBMortgageTaxonomy/60"],"eng":["https://knb.poolparty.biz/KNBMortgageTaxonomy/60"],"en":["https://knb.poolparty.biz/KNBMortgageTaxonomy/60"],"onderpand":["https://knb.poolparty.biz/KNBMortgageTaxonomy/60"],"onderpan":["https://knb.poolparty.biz/KNBMortgageTaxonomy/60"],"onderpa":["https://knb.poolparty.biz/KNBMortgageTaxonomy/60"],"onderp":["https://knb.poolparty.biz/KNBMortgageTaxonomy/60"],"onder":["https://knb.poolparty.biz/KNBMortgageTaxonomy/60"],"onde":["https://knb.poolparty.biz/KNBMortgageTaxonomy/60"],"ond":["https://knb.poolparty.biz/KNBMortgageTaxonomy/60"],"on":["https://knb.poolparty.biz/KNBMortgageTaxonomy/60"],"nderpand":["https://knb.poolparty.biz/KNBMortgageTaxonomy/60"],"nderpan":["https://knb.poolparty.biz/KNBMortgageTaxonomy/60"],"nderpa":["https://knb.poolparty.biz/KNBMortgageTaxonomy/60"],"nderp":["https://knb.poolparty.biz/KNBMortgageTaxonomy/60"],"nder":["https://knb.poolparty.biz/KNBMortgageTaxonomy/60"],"nde":["https://knb.poolparty.biz/KNBMortgageTaxonomy/60"],"nd":["https://knb.poolparty.biz/KNBMortgageTaxonomy/60"],"ht":["https://knb.poolparty.biz/KNBMortgageTaxonomy/61"],"potheek":["https://knb.poolparty.biz/KNBMortgageTaxonomy/61"],"pothee":["https://knb.poolparty.biz/KNBMortgageTaxonomy/61"],"pothe":["https://knb.poolparty.biz/KNBMortgageTaxonomy/61"],"poth":["https://knb.poolparty.biz/KNBMortgageTaxonomy/61"],"pot":["https://knb.poolparty.biz/KNBMortgageTaxonomy/61"],"po":["https://knb.poolparty.biz/KNBMortgageTaxonomy/61"],"otheek":["https://knb.poolparty.biz/KNBMortgageTaxonomy/61"],"othee":["https://knb.poolparty.biz/KNBMortgageTaxonomy/61"],"othe":["https://knb.poolparty.biz/KNBMortgageTaxonomy/61"],"oth":["https://knb.poolparty.biz/KNBMortgageTaxonomy/61"],"ot":["https://knb.poolparty.biz/KNBMortgageTaxonomy/61"],"o":["https://knb.poolparty.biz/KNBMortgageTaxonomy/61"],"wordt":["https://knb.poolparty.biz/KNBMortgageTaxonomy/61"],"word":["https://knb.poolparty.biz/KNBMortgageTaxonomy/61"],"wor":["https://knb.poolparty.biz/KNBMortgageTaxonomy/61"],"wo":["https://knb.poolparty.biz/KNBMortgageTaxonomy/61"],"w":["https://knb.poolparty.biz/KNBMortgageTaxonomy/61"],"ordt":["https://knb.poolparty.biz/KNBMortgageTaxonomy/61"],"ord":["https://knb.poolparty.biz/KNBMortgageTaxonomy/61"],"or":["https://knb.poolparty.biz/KNBMortgageTaxonomy/61"],"gevestigd":["https://knb.poolparty.biz/KNBMortgageTaxonomy/61"],"gevestig":["https://knb.poolparty.biz/KNBMortgageTaxonomy/61"],"gevesti":["https://knb.poolparty.biz/KNBMortgageTaxonomy/61"],"gevest":["https://knb.poolparty.biz/KNBMortgageTaxonomy/61"],"geves":["https://knb.poolparty.biz/KNBMortgageTaxonomy/61"],"geve":["https://knb.poolparty.biz/KNBMortgageTaxonomy/61"],"gev":["https://knb.poolparty.biz/KNBMortgageTaxonomy/61"],"ge":["https://knb.poolparty.biz/KNBMortgageTaxonomy/61"],"evestigd":["https://knb.poolparty.biz/KNBMortgageTaxonomy/61"],"evestig":["https://knb.poolparty.biz/KNBMortgageTaxonomy/61"],"evesti":["https://knb.poolparty.biz/KNBMortgageTaxonomy/61"],"evest":["https://knb.poolparty.biz/KNBMortgageTaxonomy/61"],"eves":["https://knb.poolparty.biz/KNBMortgageTaxonomy/61"],"eve":["https://knb.poolparty.biz/KNBMortgageTaxonomy/61"],"ev":["https://knb.poolparty.biz/KNBMortgageTaxonomy/61"],"vestigd":["https://knb.poolparty.biz/KNBMortgageTaxonomy/61"],"vestig":["https://knb.poolparty.biz/KNBMortgageTaxonomy/61"],"vesti":["https://knb.poolparty.biz/KNBMortgageTaxonomy/61"],"vest":["https://knb.poolparty.biz/KNBMortgageTaxonomy/61"],"ves":["https://knb.poolparty.biz/KNBMortgageTaxonomy/61"],"ve":["https://knb.poolparty.biz/KNBMortgageTaxonomy/61"]},{"emer":["https://knb.poolparty.biz/KNBMortgageTaxonomy/31","https://knb.poolparty.biz/KNBMortgageTaxonomy/59"],"eme":["https://knb.poolparty.biz/KNBMortgageTaxonomy/31","https://knb.poolparty.biz/KNBMortgageTaxonomy/59"],"em":["https://knb.poolparty.biz/KNBMortgageTaxonomy/31","https://knb.poolparty.biz/KNBMortgageTaxonomy/59"],"mer":["https://knb.poolparty.biz/KNBMortgageTaxonomy/31","https://knb.poolparty.biz/KNBMortgageTaxonomy/59"],"me":["https://knb.poolparty.biz/KNBMortgageTaxonomy/31","https://knb.poolparty.biz/KNBMortgageTaxonomy/59","https://knb.poolparty.biz/KNBMortgageTaxonomy/60"],"m":["https://knb.poolparty.biz/KNBMortgageTaxonomy/31","https://knb.poolparty.biz/KNBMortgageTaxonomy/59"],"er":["https://knb.poolparty.biz/KNBMortgageTaxonomy/31"],"drag":["https://knb.poolparty.biz/KNBMortgageTaxonomy/31"],"dra":["https://knb.poolparty.biz/KNBMortgageTaxonomy/31"],"dr":["https://knb.poolparty.biz/KNBMortgageTaxonomy/31"],"rag":["https://knb.poolparty.biz/KNBMortgageTaxonomy/31"],"ra":["https://knb.poolparty.biz/KNBMortgageTaxonomy/31"],"dat":["https://knb.poolparty.biz/KNBMortgageTaxonomy/31"],"da":["https://knb.poolparty.biz/KNBMortgageTaxonomy/31"],"hypotheekakte":["https://knb.poolparty.biz/KNBMortgageTaxonomy/31","https://knb.poolparty.biz/KNBMortgageTaxonomy/59"],"hypotheekakt":["https://knb.poolparty.biz/KNBMortgageTaxonomy/31","https://knb.poolparty.biz/KNBMortgageTaxonomy/59"],"hypotheekak":["https://knb.poolparty.biz/KNBMortgageTaxonomy/31","https://knb.poolparty.biz/KNBMortgageTaxonomy/59"],"hypotheeka":["https://knb.poolparty.biz/KNBMortgageTaxonomy/31","https://knb.poolparty.biz/KNBMortgageTaxonomy/59"],"ypotheekakte":["https://knb.poolparty.biz/KNBMortgageTaxonomy/31","https://knb.poolparty.biz/KNBMortgageTaxonomy/59"],"ypotheekakt":["https://knb.poolparty.biz/KNBMortgageTaxonomy/31","https://knb.poolparty.biz/KNBMortgageTaxonomy/59"],"ypotheekak":["https://knb.poolparty.biz/KNBMortgageTaxonomy/31","https://knb.poolparty.biz/KNBMortgageTaxonomy/59"],"ypotheeka":["https://knb.poolparty.biz/KNBMortgageTaxonomy/31","https://knb.poolparty.biz/KNBMortgageTaxonomy/59"],"potheekakte":["https://knb.poolparty.biz/KNBMortgageTaxonomy/31","https://knb.poolparty.biz/KNBMortgageTaxonomy/59"],"potheekakt":["https://knb.poolparty.biz/KNBMortgageTaxonomy/31","https://knb.poolparty.biz/KNBMortgageTaxonomy/59"],"potheekak":["https://knb.poolparty.biz/KNBMortgageTaxonomy/31","https://knb.poolparty.biz/KNBMortgageTaxonomy/59"],"potheeka":["https://knb.poolparty.biz/KNBMortgageTaxonomy/31","https://knb.poolparty.biz/KNBMortgageTaxonomy/59"],"knemer":["https://knb.poolparty.biz/KNBMortgageTaxonomy/59"],"kneme":["https://knb.poolparty.biz/KNBMortgageTaxonomy/59"],"knem":["https://knb.poolparty.biz/KNBMortgageTaxonomy/59"],"kne":["https://knb.poolparty.biz/KNBMortgageTaxonomy/59"],"kn":["https://knb.poolparty.biz/KNBMortgageTaxonomy/59"],"k":["https://knb.poolparty.biz/KNBMortgageTaxonomy/59"],"nemer":["https://knb.poolparty.biz/KNBMortgageTaxonomy/59"],"neme":["https://knb.poolparty.biz/KNBMortgageTaxonomy/59"],"nem":["https://knb.poolparty.biz/KNBMortgageTaxonomy/59"],"ne":["https://knb.poolparty.biz/KNBMortgageTaxonomy/59"],"jvingsbedrag":["https://knb.poolparty.biz/KNBMortgageTaxonomy/59"],"jvingsbedra":["https://knb.poolparty.biz/KNBMortgageTaxonomy/59"],"jvingsbedr":["https://knb.poolparty.biz/KNBMortgageTaxonomy/59"],"jvingsbed":["https://knb.poolparty.biz/KNBMortgageTaxonomy/59"],"jvingsbe":["https://knb.poolparty.biz/KNBMortgageTaxonomy/59"],"jvingsb":["https://knb.poolparty.biz/KNBMortgageTaxonomy/59"],"jvings":["https://knb.poolparty.biz/KNBMortgageTaxonomy/59"],"jving":["https://knb.poolparty.biz/KNBMortgageTaxonomy/59"],"jvin":["https://knb.poolparty.biz/KNBMortgageTaxonomy/59"],"jvi":["https://knb.poolparty.biz/KNBMortgageTaxonomy/59"],"jv":["https://knb.poolparty.biz/KNBMortgageTaxonomy/59"],"j":["https://knb.poolparty.biz/KNBMortgageTaxonomy/59"],"vingsbedrag":["https://knb.poolparty.biz/KNBMortgageTaxonomy/59"],"vingsbedra":["https://knb.poolparty.biz/KNBMortgageTaxonomy/59"],"vingsbedr":["https://knb.poolparty.biz/KNBMortgageTaxonomy/59"],"vingsbed":["https://knb.poolparty.biz/KNBMortgageTaxonomy/59"],"vingsbe":["https://knb.poolparty.biz/KNBMortgageTaxonomy/59"],"vingsb":["https://knb.poolparty.biz/KNBMortgageTaxonomy/59"],"vings":["https://knb.poolparty.biz/KNBMortgageTaxonomy/59"],"ving":["https://knb.poolparty.biz/KNBMortgageTaxonomy/59"],"vin":["https://knb.poolparty.biz/KNBMortgageTaxonomy/59"],"vi":["https://knb.poolparty.biz/KNBMortgageTaxonomy/59"],"v":["https://knb.poolparty.biz/KNBMortgageTaxonomy/59"],"ingsbedrag":["https://knb.poolparty.biz/KNBMortgageTaxonomy/59"],"ingsbedra":["https://knb.poolparty.biz/KNBMortgageTaxonomy/59"],"ingsbedr":["https://knb.poolparty.biz/KNBMortgageTaxonomy/59"],"ingsbed":["https://knb.poolparty.biz/KNBMortgageTaxonomy/59"],"ingsbe":["https://knb.poolparty.biz/KNBMortgageTaxonomy/59"],"ingsb":["https://knb.poolparty.biz/KNBMortgageTaxonomy/59"],"ings":["https://knb.poolparty.biz/KNBMortgageTaxonomy/59"],"ing":["https://knb.poolparty.biz/KNBMortgageTaxonomy/59"],"ngsbedrag":["https://knb.poolparty.biz/KNBMortgageTaxonomy/59"],"ngsbedra":["https://knb.poolparty.biz/KNBMortgageTaxonomy/59"],"ngsbedr":["https://knb.poolparty.biz/KNBMortgageTaxonomy/59"],"ngsbed":["https://knb.poolparty.biz/KNBMortgageTaxonomy/59"],"ngsbe":["https://knb.poolparty.biz/KNBMortgageTaxonomy/59"],"ngsb":["https://knb.poolparty.biz/KNBMortgageTaxonomy/59"],"ngs":["https://knb.poolparty.biz/KNBMortgageTaxonomy/59","https://knb.poolparty.biz/KNBMortgageTaxonomy/60"],"ng":["https://knb.poolparty.biz/KNBMortgageTaxonomy/59","https://knb.poolparty.biz/KNBMortgageTaxonomy/60"],"op":["https://knb.poolparty.biz/KNBMortgageTaxonomy/59"],"basis":["https://knb.poolparty.biz/KNBMortgageTaxonomy/59"],"basi":["https://knb.poolparty.biz/KNBMortgageTaxonomy/59"],"bas":["https://knb.poolparty.biz/KNBMortgageTaxonomy/59"],"ba":["https://knb.poolparty.biz/KNBMortgageTaxonomy/59"],"asis":["https://knb.poolparty.biz/KNBMortgageTaxonomy/59"],"asi":["https://knb.poolparty.biz/KNBMortgageTaxonomy/59"],"al":["https://knb.poolparty.biz/KNBMortgageTaxonomy/60"],"l":["https://knb.poolparty.biz/KNBMortgageTaxonomy/60"],"ngst":["https://knb.poolparty.biz/KNBMortgageTaxonomy/60"],"gst":["https://knb.poolparty.biz/KNBMortgageTaxonomy/60"],"gs":["https://knb.poolparty.biz/KNBMortgageTaxonomy/60"],"st":["https://knb.poolparty.biz/KNBMortgageTaxonomy/60","https://knb.poolparty.biz/KNBMortgageTaxonomy/61"],"s":["https://knb.poolparty.biz/KNBMortgageTaxonomy/60","https://knb.poolparty.biz/KNBMortgageTaxonomy/61"],"derpand":["https://knb.poolparty.biz/KNBMortgageTaxonomy/60"],"derpan":["https://knb.poolparty.biz/KNBMortgageTaxonomy/60"],"derpa":["https://knb.poolparty.biz/KNBMortgageTaxonomy/60"],"derp":["https://knb.poolparty.biz/KNBMortgageTaxonomy/60"],"der":["https://knb.poolparty.biz/KNBMortgageTaxonomy/60"],"erpand":["https://knb.poolparty.biz/KNBMortgageTaxonomy/60"],"erpan":["https://knb.poolparty.biz/KNBMortgageTaxonomy/60"],"erpa":["https://knb.poolparty.biz/KNBMortgageTaxonomy/60"],"erp":["https://knb.poolparty.biz/KNBMortgageTaxonomy/60"],"rpand":["https://knb.poolparty.biz/KNBMortgageTaxonomy/60"],"rpan":["https://knb.poolparty.biz/KNBMortgageTaxonomy/60"],"rpa":["https://knb.poolparty.biz/KNBMortgageTaxonomy/60"],"rp":["https://knb.poolparty.biz/KNBMortgageTaxonomy/60"],"met":["https://knb.poolparty.biz/KNBMortgageTaxonomy/60"],"voorrang":["https://knb.poolparty.biz/KNBMortgageTaxonomy/60"],"voorran":["https://knb.poolparty.biz/KNBMortgageTaxonomy/60"],"voorra":["https://knb.poolparty.biz/KNBMortgageTaxonomy/60"],"voorr":["https://knb.poolparty.biz/KNBMortgageTaxonomy/60"],"voor":["https://knb.poolparty.biz/KNBMortgageTaxonomy/60"],"voo":["https://knb.poolparty.biz/KNBMortgageTaxonomy/60"],"vo":["https://knb.poolparty.biz/KNBMortgageTaxonomy/60"],"oorrang":["https://knb.poolparty.biz/KNBMortgageTaxonomy/60"],"oorran":["https://knb.poolparty.biz/KNBMortgageTaxonomy/60"],"oorra":["https://knb.poolparty.biz/KNBMortgageTaxonomy/60"],"oorr":["https://knb.poolparty.biz/KNBMortgageTaxonomy/60"],"oor":["https://knb.poolparty.biz/KNBMortgageTaxonomy/60"],"orrang":["https://knb.poolparty.biz/KNBMortgageTaxonomy/60"],"orran":["https://knb.poolparty.biz/KNBMortgageTaxonomy/60"],"orra":["https://knb.poolparty.biz/KNBMortgageTaxonomy/60"],"orr":["https://knb.poolparty.biz/KNBMortgageTaxonomy/60"],"or":["https://knb.poolparty.biz/KNBMortgageTaxonomy/60"],"schuldeisers":["https://knb.poolparty.biz/KNBMortgageTaxonomy/60"],"schuldeiser":["https://knb.poolparty.biz/KNBMortgageTaxonomy/60"],"schuldeise":["https://knb.poolparty.biz/KNBMortgageTaxonomy/60"],"schuldeis":["https://knb.poolparty.biz/KNBMortgageTaxonomy/60"],"schuldei":["https://knb.poolparty.biz/KNBMortgageTaxonomy/60"],"schulde":["https://knb.poolparty.biz/KNBMortgageTaxonomy/60"],"schuld":["https://knb.poolparty.biz/KNBMortgageTaxonomy/60"],"schul":["https://knb.poolparty.biz/KNBMortgageTaxonomy/60"],"schu":["https://knb.poolparty.biz/KNBMortgageTaxonomy/60"],"sch":["https://knb.poolparty.biz/KNBMortgageTaxonomy/60"],"sc":["https://knb.poolparty.biz/KNBMortgageTaxonomy/60"],"chuldeisers":["https://knb.poolparty.biz/KNBMortgageTaxonomy/60"],"chuldeiser":["https://knb.poolparty.biz/KNBMortgageTaxonomy/60"],"chuldeise":["https://knb.poolparty.biz/KNBMortgageTaxonomy/60"],"chuldeis":["https://knb.poolparty.biz/KNBMortgageTaxonomy/60"],"chuldei":["https://knb.poolparty.biz/KNBMortgageTaxonomy/60"],"chulde":["https://knb.poolparty.biz/KNBMortgageTaxonomy/60"],"chuld":["https://knb.poolparty.biz/KNBMortgageTaxonomy/60"],"chul":["https://knb.poolparty.biz/KNBMortgageTaxonomy/60"],"chu":["https://knb.poolparty.biz/KNBMortgageTaxonomy/60"],"ch":["https://knb.poolparty.biz/KNBMortgageTaxonomy/60"],"c":["https://knb.poolparty.biz/KNBMortgageTaxonomy/60"],"heek":["https://knb.poolparty.biz/KNBMortgageTaxonomy/61"],"hee":["https://knb.poolparty.biz/KNBMortgageTaxonomy/61"],"eek":["https://knb.poolparty.biz/KNBMortgageTaxonomy/61"],"ee":["https://knb.poolparty.biz/KNBMortgageTaxonomy/61"],"rdt":["https://knb.poolparty.biz/KNBMortgageTaxonomy/61"],"rd":["https://knb.poolparty.biz/KNBMortgageTaxonomy/61"],"dt":["https://knb.poolparty.biz/KNBMortgageTaxonomy/61"],"d":["https://knb.poolparty.biz/KNBMortgageTaxonomy/61"],"estigd":["https://knb.poolparty.biz/KNBMortgageTaxonomy/61"],"estig":["https://knb.poolparty.biz/KNBMortgageTaxonomy/61"],"esti":["https://knb.poolparty.biz/KNBMortgageTaxonomy/61"],"est":["https://knb.poolparty.biz/KNBMortgageTaxonomy/61"],"es":["https://knb.poolparty.biz/KNBMortgageTaxonomy/61"],"stigd":["https://knb.poolparty.biz/KNBMortgageTaxonomy/61"],"stig":["https://knb.poolparty.biz/KNBMortgageTaxonomy/61"],"sti":["https://knb.poolparty.biz/KNBMortgageTaxonomy/61"],"onderpand":["https://knb.poolparty.biz/KNBMortgageTaxonomy/61"],"onderpan":["https://knb.poolparty.biz/KNBMortgageTaxonomy/61"],"onderpa":["https://knb.poolparty.biz/KNBMortgageTaxonomy/61"],"onderp":["https://knb.poolparty.biz/KNBMortgageTaxonomy/61"],"onder":["https://knb.poolparty.biz/KNBMortgageTaxonomy/61"],"onde":["https://knb.poolparty.biz/KNBMortgageTaxonomy/61"],"ond":["https://knb.poolparty.biz/KNBMortgageTaxonomy/61"],"on":["https://knb.poolparty.biz/KNBMortgageTaxonomy/61"],"nderpand":["https://knb.poolparty.biz/KNBMortgageTaxonomy/61"],"nderpan":["https://knb.poolparty.biz/KNBMortgageTaxonomy/61"],"nderpa":["https://knb.poolparty.biz/KNBMortgageTaxonomy/61"],"nderp":["https://knb.poolparty.biz/KNBMortgageTaxonomy/61"],"nder":["https://knb.poolparty.biz/KNBMortgageTaxonomy/61"],"nde":["https://knb.poolparty.biz/KNBMortgageTaxonomy/61"],"nd":["https://knb.poolparty.biz/KNBMortgageTaxonomy/61"]},{"r":["https://knb.poolparty.biz/KNBMortgageTaxonomy/31"],"at":["https://knb.poolparty.biz/KNBMortgageTaxonomy/31"],"in":["https://knb.poolparty.biz/KNBMortgageTaxonomy/31"],"otheekakte":["https://knb.poolparty.biz/KNBMortgageTaxonomy/31","https://knb.poolparty.biz/KNBMortgageTaxonomy/59"],"otheekakt":["https://knb.poolparty.biz/KNBMortgageTaxonomy/31","https://knb.poolparty.biz/KNBMortgageTaxonomy/59"],"otheekak":["https://knb.poolparty.biz/KNBMortgageTaxonomy/31","https://knb.poolparty.biz/KNBMortgageTaxonomy/59"],"otheeka":["https://knb.poolparty.biz/KNBMortgageTaxonomy/31","https://knb.poolparty.biz/KNBMortgageTaxonomy/59"],"theekakte":["https://knb.poolparty.biz/KNBMortgageTaxonomy/31","https://knb.poolparty.biz/KNBMortgageTaxonomy/59"],"theekakt":["https://knb.poolparty.biz/KNBMortgageTaxonomy/31","https://knb.poolparty.biz/KNBMortgageTaxonomy/59"],"theekak":["https://knb.poolparty.biz/KNBMortgageTaxonomy/31","https://knb.poolparty.biz/KNBMortgageTaxonomy/59"],"theeka":["https://knb.poolparty.biz/KNBMortgageTaxonomy/31","https://knb.poolparty.biz/KNBMortgageTaxonomy/59"],"heekakte":["https://knb.poolparty.biz/KNBMortgageTaxonomy/31","https://knb.poolparty.biz/KNBMortgageTaxonomy/59"],"heekakt":["https://knb.poolparty.biz/KNBMortgageTaxonomy/31","https://knb.poolparty.biz/KNBMortgageTaxonomy/59"],"heekak":["https://knb.poolparty.biz/KNBMortgageTaxonomy/31","https://knb.poolparty.biz/KNBMortgageTaxonomy/59"],"heeka":["https://knb.poolparty.biz/KNBMortgageTaxonomy/31","https://knb.poolparty.biz/KNBMortgageTaxonomy/59"],"eekakte":["https://knb.poolparty.biz/KNBMortgageTaxonomy/31","https://knb.poolparty.biz/KNBMortgageTaxonomy/59"],"eekakt":["https://knb.poolparty.biz/KNBMortgageTaxonomy/31","https://knb.poolparty.biz/KNBMortgageTaxonomy/59"],"eekak":["https://knb.poolparty.biz/KNBMortgageTaxonomy/31","https://knb.poolparty.biz/KNBMortgageTaxonomy/59"],"eeka":["https://knb.poolparty.biz/KNBMortgageTaxonomy/31","https://knb.poolparty.biz/KNBMortgageTaxonomy/59"],"staat":["https://knb.poolparty.biz/KNBMortgageTaxonomy/31"],"staa":["https://knb.poolparty.biz/KNBMortgageTaxonomy/31"],"sta":["https://knb.poolparty.biz/KNBMortgageTaxonomy/31"],"st":["https://knb.poolparty.biz/KNBMortgageTaxonomy/31"],"s":["https://knb.poolparty.biz/KNBMortgageTaxonomy/31"],"er":["https://knb.poolparty.biz/KNBMortgageTaxonomy/59","https://knb.poolparty.biz/KNBMortgageTaxonomy/61"],"gsbedrag":["https://knb.poolparty.biz/KNBMortgageTaxonomy/59"],"gsbedra":["https://knb.poolparty.biz/KNBMortgageTaxonomy/59"],"gsbedr":["https://knb.poolparty.biz/KNBMortgageTaxonomy/59"],"gsbed":["https://knb.poolparty.biz/KNBMortgageTaxonomy/59"],"gsbe":["https://knb.poolparty.biz/KNBMortgageTaxonomy/59"],"gsb":["https://knb.poolparty.biz/KNBMortgageTaxonomy/59"],"gs":["https://knb.poolparty.biz/KNBMortgageTaxonomy/59"],"sbedrag":["https://knb.poolparty.biz/KNBMortgageTaxonomy/59"],"sbedra":["https://knb.poolparty.biz/KNBMortgageTaxonomy/59"],"sbedr":["https://knb.poolparty.biz/KNBMortgageTaxonomy/59"],"sbed":["https://knb.poolparty.biz/KNBMortgageTaxonomy/59"],"sbe":["https://knb.poolparty.biz/KNBMortgageTaxonomy/59"],"sb":["https://knb.poolparty.biz/KNBMortgageTaxonomy/59"],"sis":["https://knb.poolparty.biz/KNBMortgageTaxonomy/59"],"si":["https://knb.poolparty.biz/KNBMortgageTaxonomy/59"],"is":["https://knb.poolparty.biz/KNBMortgageTaxonomy/59"],"van":["https://knb.poolparty.biz/KNBMortgageTaxonomy/59"],"va":["https://knb.poolparty.biz/KNBMortgageTaxonomy/59"],"an":["https://knb.poolparty.biz/KNBMortgageTaxonomy/59"],"maximaal":["https://knb.poolparty.biz/KNBMortgageTaxonomy/59"],"maximaa":["https://knb.poolparty.biz/KNBMortgageTaxonomy/59"],"maxima":["https://knb.poolparty.biz/KNBMortgageTaxonomy/59"],"maxim":["https://knb.poolparty.biz/KNBMortgageTaxonomy/59"],"maxi":["https://knb.poolparty.biz/KNBMortgageTaxonomy/59"],"max":["https://knb.poolparty.biz/KNBMortgageTaxonomy/59"],"ma":["https://knb.poolparty.biz/KNBMortgageTaxonomy/59"],"aximaal":["https://knb.poolparty.biz/KNBMortgageTaxonomy/59"],"aximaa":["https://knb.poolparty.biz/KNBMortgageTaxonomy/59"],"axima":["https://knb.poolparty.biz/KNBMortgageTaxonomy/59"],"axim":["https://knb.poolparty.biz/KNBMortgageTaxonomy/59"],"axi":["https://knb.poolparty.biz/KNBMortgageTaxonomy/59"],"ax":["https://knb.poolparty.biz/KNBMortgageTaxonomy/59"],"ximaal":["https://knb.poolparty.biz/KNBMortgageTaxonomy/59"],"ximaa":["https://knb.poolparty.biz/KNBMortgageTaxonomy/59"],"xima":["https://knb.poolparty.biz/KNBMortgageTaxonomy/59"],"xim":["https://knb.poolparty.biz/KNBMortgageTaxonomy/59"],"xi":["https://knb.poolparty.biz/KNBMortgageTaxonomy/59"],"x":["https://knb.poolparty.biz/KNBMortgageTaxonomy/59"],"pand":["https://knb.poolparty.biz/KNBMortgageTaxonomy/60"],"pan":["https://knb.poolparty.biz/KNBMortgageTaxonomy/60"],"pa":["https://knb.poolparty.biz/KNBMortgageTaxonomy/60"],"and":["https://knb.poolparty.biz/KNBMortgageTaxonomy/60"],"rrang":["https://knb.poolparty.biz/KNBMortgageTaxonomy/60"],"rran":["https://knb.poolparty.biz/KNBMortgageTaxonomy/60"],"rra":["https://knb.poolparty.biz/KNBMortgageTaxonomy/60"],"rr":["https://knb.poolparty.biz/KNBMortgageTaxonomy/60"],"rang":["https://knb.poolparty.biz/KNBMortgageTaxonomy/60"],"ran":["https://knb.poolparty.biz/KNBMortgageTaxonomy/60"],"ang":["https://knb.poolparty.biz/KNBMortgageTaxonomy/60"],"andere":["https://knb.poolparty.biz/KNBMortgageTaxonomy/60"],"ander":["https://knb.poolparty.biz/KNBMortgageTaxonomy/60"],"ande":["https://knb.poolparty.biz/KNBMortgageTaxonomy/60"],"ndere":["https://knb.poolparty.biz/KNBMortgageTaxonomy/60"],"dere":["https://knb.poolparty.biz/KNBMortgageTaxonomy/60"],"huldeisers":["https://knb.poolparty.biz/KNBMortgageTaxonomy/60"],"huldeiser":["https://knb.poolparty.biz/KNBMortgageTaxonomy/60"],"huldeise":["https://knb.poolparty.biz/KNBMortgageTaxonomy/60"],"huldeis":["https://knb.poolparty.biz/KNBMortgageTaxonomy/60"],"huldei":["https://knb.poolparty.biz/KNBMortgageTaxonomy/60"],"hulde":["https://knb.poolparty.biz/KNBMortgageTaxonomy/60"],"huld":["https://knb.poolparty.biz/KNBMortgageTaxonomy/60"],"hul":["https://knb.poolparty.biz/KNBMortgageTaxonomy/60"],"hu":["https://knb.poolparty.biz/KNBMortgageTaxonomy/60"],"uldeisers":["https://knb.poolparty.biz/KNBMortgageTaxonomy/60"],"uldeiser":["https://knb.poolparty.biz/KNBMortgageTaxonomy/60"],"uldeise":["https://knb.poolparty.biz/KNBMortgageTaxonomy/60"],"uldeis":["https://knb.poolparty.biz/KNBMortgageTaxonomy/60"],"uldei":["https://knb.poolparty.biz/KNBMortgageTaxonomy/60"],"ulde":["https://knb.poolparty.biz/KNBMortgageTaxonomy/60"],"uld":["https://knb.poolparty.biz/KNBMortgageTaxonomy/60"],"ul":["https://knb.poolparty.biz/KNBMortgageTaxonomy/60"],"u":["https://knb.poolparty.biz/KNBMortgageTaxonomy/60"],"ldeisers":["https://knb.poolparty.biz/KNBMortgageTaxonomy/60"],"ldeiser":["https://knb.poolparty.biz/KNBMortgageTaxonomy/60"],"ldeise":["https://knb.poolparty.biz/KNBMortgageTaxonomy/60"],"ldeis":["https://knb.poolparty.biz/KNBMortgageTaxonomy/60"],"ldei":["https://knb.poolparty.biz/KNBMortgageTaxonomy/60"],"lde":["https://knb.poolparty.biz/KNBMortgageTaxonomy/60"],"ld":["https://knb.poolparty.biz/KNBMortgageTaxonomy/60"],"deisers":["https://knb.poolparty.biz/KNBMortgageTaxonomy/60"],"deiser":["https://knb.poolparty.biz/KNBMortgageTaxonomy/60"],"deise":["https://knb.poolparty.biz/KNBMortgageTaxonomy/60"],"deis":["https://knb.poolparty.biz/KNBMortgageTaxonomy/60"],"dei":["https://knb.poolparty.biz/KNBMortgageTaxonomy/60"],"ek":["https://knb.poolparty.biz/KNBMortgageTaxonomy/61"],"k":["https://knb.poolparty.biz/KNBMortgageTaxonomy/61"],"tigd":["https://knb.poolparty.biz/KNBMortgageTaxonomy/61"],"tig":["https://knb.poolparty.biz/KNBMortgageTaxonomy/61"],"ti":["https://knb.poolparty.biz/KNBMortgageTaxonomy/61"],"igd":["https://knb.poolparty.biz/KNBMortgageTaxonomy/61"],"ig":["https://knb.poolparty.biz/KNBMortgageTaxonomy/61"],"i":["https://knb.poolparty.biz/KNBMortgageTaxonomy/61"],"op":["https://knb.poolparty.biz/KNBMortgageTaxonomy/61"],"derpand":["https://knb.poolparty.biz/KNBMortgageTaxonomy/61"],"derpan":["https://knb.poolparty.biz/KNBMortgageTaxonomy/61"],"derpa":["https://knb.poolparty.biz/KNBMortgageTaxonomy/61"],"derp":["https://knb.poolparty.biz/KNBMortgageTaxonomy/61"],"der":["https://knb.poolparty.biz/KNBMortgageTaxonomy/61"],"de":["https://knb.poolparty.biz/KNBMortgageTaxonomy/61"],"erpand":["https://knb.poolparty.biz/KNBMortgageTaxonomy/61"],"erpan":["https://knb.poolparty.biz/KNBMortgageTaxonomy/61"],"erpa":["https://knb.poolparty.biz/KNBMortgageTaxonomy/61"],"erp":["https://knb.poolparty.biz/KNBMortgageTaxonomy/61"]},{"ekakte":["https://knb.poolparty.biz/KNBMortgageTaxonomy/31","https://knb.poolparty.biz/KNBMortgageTaxonomy/59"],"ekakt":["https://knb.poolparty.biz/KNBMortgageTaxonomy/31","https://knb.poolparty.biz/KNBMortgageTaxonomy/59"],"ekak":["https://knb.poolparty.biz/KNBMortgageTaxonomy/31","https://knb.poolparty.biz/KNBMortgageTaxonomy/59"],"eka":["https://knb.poolparty.biz/KNBMortgageTaxonomy/31","https://knb.poolparty.biz/KNBMortgageTaxonomy/59"],"kakte":["https://knb.poolparty.biz/KNBMortgageTaxonomy/31","https://knb.poolparty.biz/KNBMortgageTaxonomy/59"],"kakt":["https://knb.poolparty.biz/KNBMortgageTaxonomy/31","https://knb.poolparty.biz/KNBMortgageTaxonomy/59"],"kak":["https://knb.poolparty.biz/KNBMortgageTaxonomy/31","https://knb.poolparty.biz/KNBMortgageTaxonomy/59"],"ka":["https://knb.poolparty.biz/KNBMortgageTaxonomy/31","https://knb.poolparty.biz/KNBMortgageTaxonomy/59"],"akte":["https://knb.poolparty.biz/KNBMortgageTaxonomy/31","https://knb.poolparty.biz/KNBMortgageTaxonomy/59"],"akt":["https://knb.poolparty.biz/KNBMortgageTaxonomy/31","https://knb.poolparty.biz/KNBMortgageTaxonomy/59"],"ak":["https://knb.poolparty.biz/KNBMortgageTaxonomy/31","https://knb.poolparty.biz/KNBMortgageTaxonomy/59"],"taat":["https://knb.poolparty.biz/KNBMortgageTaxonomy/31"],"taa":["https://knb.poolparty.biz/KNBMortgageTaxonomy/31"],"ta":["https://knb.poolparty.biz/KNBMortgageTaxonomy/31"],"aat":["https://knb.poolparty.biz/KNBMortgageTaxonomy/31"],"aa":["https://knb.poolparty.biz/KNBMortgageTaxonomy/31"],"de":["https://knb.poolparty.biz/KNBMortgageTaxonomy/59"],"kte":["https://knb.poolparty.biz/KNBMortgageTaxonomy/59"],"kt":["https://knb.poolparty.biz/KNBMortgageTaxonomy/59"],"imaal":["https://knb.poolparty.biz/KNBMortgageTaxonomy/59"],"imaa":["https://knb.poolparty.biz/KNBMortgageTaxonomy/59"],"ima":["https://knb.poolparty.biz/KNBMortgageTaxonomy/59"],"im":["https://knb.poolparty.biz/KNBMortgageTaxonomy/59"],"maal":["https://knb.poolparty.biz/KNBMortgageTaxonomy/59"],"maa":["https://knb.poolparty.biz/KNBMortgageTaxonomy/59"],"aal":["https://knb.poolparty.biz/KNBMortgageTaxonomy/59"],"mag":["https://knb.poolparty.biz/KNBMortgageTaxonomy/59"],"opeisen":["https://knb.poolparty.biz/KNBMortgageTaxonomy/59"],"opeise":["https://knb.poolparty.biz/KNBMortgageTaxonomy/59"],"opeis":["https://knb.poolparty.biz/KNBMortgageTaxonomy/59"],"opei":["https://knb.poolparty.biz/KNBMortgageTaxonomy/59"],"ope":["https://knb.poolparty.biz/KNBMortgageTaxonomy/59"],"peisen":["https://knb.poolparty.biz/KNBMortgageTaxonomy/59"],"peise":["https://knb.poolparty.biz/KNBMortgageTaxonomy/59"],"peis":["https://knb.poolparty.biz/KNBMortgageTaxonomy/59"],"pei":["https://knb.poolparty.biz/KNBMortgageTaxonomy/59"],"pe":["https://knb.poolparty.biz/KNBMortgageTaxonomy/59"],"eisen":["https://knb.poolparty.biz/KNBMortgageTaxonomy/59"],"eise":["https://knb.poolparty.biz/KNBMortgageTaxonomy/59","https://knb.poolparty.biz/KNBMortgageTaxonomy/60"],"eis":["https://knb.poolparty.biz/KNBMortgageTaxonomy/59","https://knb.poolparty.biz/KNBMortgageTaxonomy/60"],"ei":["https://knb.poolparty.biz/KNBMortgageTaxonomy/59","https://knb.poolparty.biz/KNBMortgageTaxonomy/60"],"ere":["https://knb.poolparty.biz/KNBMortgageTaxonomy/60"],"eisers":["https://knb.poolparty.biz/KNBMortgageTaxonomy/60"],"eiser":["https://knb.poolparty.biz/KNBMortgageTaxonomy/60"],"isers":["https://knb.poolparty.biz/KNBMortgageTaxonomy/60"],"iser":["https://knb.poolparty.biz/KNBMortgageTaxonomy/60"],"ise":["https://knb.poolparty.biz/KNBMortgageTaxonomy/60"],"is":["https://knb.poolparty.biz/KNBMortgageTaxonomy/60"],"sers":["https://knb.poolparty.biz/KNBMortgageTaxonomy/60"],"ser":["https://knb.poolparty.biz/KNBMortgageTaxonomy/60"],"se":["https://knb.poolparty.biz/KNBMortgageTaxonomy/60"],"ers":["https://knb.poolparty.biz/KNBMortgageTaxonomy/60"],"ten":["https://knb.poolparty.biz/KNBMortgageTaxonomy/60"],"goede":["https://knb.poolparty.biz/KNBMortgageTaxonomy/60"],"goed":["https://knb.poolparty.biz/KNBMortgageTaxonomy/60"],"goe":["https://knb.poolparty.biz/KNBMortgageTaxonomy/60"],"go":["https://knb.poolparty.biz/KNBMortgageTaxonomy/60"],"oede":["https://knb.poolparty.biz/KNBMortgageTaxonomy/60"],"oed":["https://knb.poolparty.biz/KNBMortgageTaxonomy/60"],"oe":["https://knb.poolparty.biz/KNBMortgageTaxonomy/60"],"ede":["https://knb.poolparty.biz/KNBMortgageTaxonomy/60"],"komen":["https://knb.poolparty.biz/KNBMortgageTaxonomy/60"],"kome":["https://knb.poolparty.biz/KNBMortgageTaxonomy/60"],"kom":["https://knb.poolparty.biz/KNBMortgageTaxonomy/60"],"ko":["https://knb.poolparty.biz/KNBMortgageTaxonomy/60"],"k":["https://knb.poolparty.biz/KNBMortgageTaxonomy/60"],"gd":["https://knb.poolparty.biz/KNBMortgageTaxonomy/61"],"rpand":["https://knb.poolparty.biz/KNBMortgageTaxonomy/61"],"rpan":["https://knb.poolparty.biz/KNBMortgageTaxonomy/61"],"rpa":["https://knb.poolparty.biz/KNBMortgageTaxonomy/61"],"rp":["https://knb.poolparty.biz/KNBMortgageTaxonomy/61"],"pand":["https://knb.poolparty.biz/KNBMortgageTaxonomy/61"],"pan":["https://knb.poolparty.biz/KNBMortgageTaxonomy/61"],"pa":["https://knb.poolparty.biz/KNBMortgageTaxonomy/61"],"and":["https://knb.poolparty.biz/KNBMortgageTaxonomy/61"]},{"kte":["https://knb.poolparty.biz/KNBMortgageTaxonomy/31"],"kt":["https://knb.poolparty.biz/KNBMortgageTaxonomy/31"],"te":["https://knb.poolparty.biz/KNBMortgageTaxonomy/31","https://knb.poolparty.biz/KNBMortgageTaxonomy/59"],"al":["https://knb.poolparty.biz/KNBMortgageTaxonomy/59"],"l":["https://knb.poolparty.biz/KNBMortgageTaxonomy/59"],"isen":["https://knb.poolparty.biz/KNBMortgageTaxonomy/59"],"ise":["https://knb.poolparty.biz/KNBMortgageTaxonomy/59"],"sen":["https://knb.poolparty.biz/KNBMortgageTaxonomy/59"],"se":["https://knb.poolparty.biz/KNBMortgageTaxonomy/59"],"rs":["https://knb.poolparty.biz/KNBMortgageTaxonomy/60"],"mag":["https://knb.poolparty.biz/KNBMortgageTaxonomy/60"],"omen":["https://knb.poolparty.biz/KNBMortgageTaxonomy/60"],"ome":["https://knb.poolparty.biz/KNBMortgageTaxonomy/60"],"om":["https://knb.poolparty.biz/KNBMortgageTaxonomy/60"],"men":["https://knb.poolparty.biz/KNBMortgageTaxonomy/60"]},{}]